{
    "roi": {
        "km": 2,
        "side": 500,
        "center_lat": 0.0,
        "center_lon": 0.0
    },
    "sensors": [
        {
            "_id": 0,
            "lat": -0.004633417170640772,
            "lon": 0.0028662802050085662,
            "offload": 72
        },
        {
            "_id": 1,
            "lat": 0.003277791860371672,
            "lon": -0.006785697659859544,
            "offload": 212
        },
        {
            "_id": 2,
            "lat": 0.006077800880898626,
            "lon": -0.0064364264371329655,
            "offload": 180
        },
        {
            "_id": 3,
            "lat": 0.003907233688075079,
            "lon": -0.0002530641789979266,
            "offload": 137
        },
        {
            "_id": 4,
            "lat": -0.00540418416489034,
            "lon": 0.0018006639346199692,
            "offload": 104
        },
        {
            "_id": 5,
            "lat": 0.005056581792236664,
            "lon": -0.004630903511727569,
            "offload": 248
        },
        {
            "_id": 6,
            "lat": 0.0006586832830523612,
            "lon": 0.005561495780963691,
            "offload": 207
        },
        {
            "_id": 7,
            "lat": -0.007743848049297274,
            "lon": 0.008737335732410298,
            "offload": 67
        },
        {
            "_id": 8,
            "lat": -0.00042171136115118184,
            "lon": 0.008948151297217946,
            "offload": 232
        },
        {
            "_id": 9,
            "lat": 0.005996557294710549,
            "lon": 0.00759030022139482,
            "offload": 224
        },
        {
            "_id": 10,
            "lat": -0.0065033954646761555,
            "lon": 0.003869977853081028,
            "offload": 150
        },
        {
            "_id": 11,
            "lat": 0.008947976901385364,
            "lon": 0.004425816869805576,
            "offload": 202
        },
        {
            "_id": 12,
            "lat": -0.006402755483051169,
            "lon": -0.007562263772753458,
            "offload": 65
        },
        {
            "_id": 13,
            "lat": -0.0005201534701049365,
            "lon": -0.004757146212384088,
            "offload": 90
        },
        {
            "_id": 14,
            "lat": -0.0027839877633601432,
            "lon": -0.000939210184745902,
            "offload": 128
        },
        {
            "_id": 15,
            "lat": -0.00862333043541048,
            "lon": -0.0019644613683376467,
            "offload": 171
        },
        {
            "_id": 16,
            "lat": 0.005723799145976344,
            "lon": -0.005208953134811544,
            "offload": 76
        },
        {
            "_id": 17,
            "lat": 0.004054683407032246,
            "lon": 0.008042279209238341,
            "offload": 92
        },
        {
            "_id": 18,
            "lat": -0.005787074819170667,
            "lon": 0.003808451049576219,
            "offload": 114
        },
        {
            "_id": 19,
            "lat": -0.004658946981043526,
            "lon": 0.0004057052372734675,
            "offload": 191
        },
        {
            "_id": 20,
            "lat": -0.003883264990156441,
            "lon": 0.005225101655266191,
            "offload": 92
        },
        {
            "_id": 21,
            "lat": -0.004407963757144465,
            "lon": -0.004932760776791948,
            "offload": 139
        },
        {
            "_id": 22,
            "lat": 0.00037794662048730096,
            "lon": -0.000481752693015966,
            "offload": 250
        },
        {
            "_id": 23,
            "lat": -0.004036904631283606,
            "lon": -0.0012736003947950124,
            "offload": 83
        },
        {
            "_id": 24,
            "lat": 0.008576593712170797,
            "lon": -0.006318435516763352,
            "offload": 221
        }
    ]
}